[
    {
        "name": "AnimePahe (EN)",
        "results": {
            "popular": {
                "result": [
                    {
                        "animes": [
                            {
                                "url": "/anime/?anime_id=5587",
                                "title": "Code Geass: Dakkan no Rozé",
                                "artist": "Disney_Plus",
                                "thumbnail_url": "https://i.animepahe.ru/snapshots/3c8740c2fa6630e8a96db63d63e7e21a4ec3d8ba3a429df0a393690de6abc82c.jpg"
                            },
                            {
                                "url": "/anime/?anime_id=5584",
                                "title": "Dead Dead Demons Dededede Destruction (ONA)",
                                "artist": "SubsPlease",
                                "thumbnail_url": "https://i.animepahe.ru/snapshots/7ac832382caf39e53677ca8df68a859d49c2ceb616f2ef062314395ecfe7ad3a.jpg"
                            },
                            {
                                "url": "/anime/?anime_id=5606",
                                "title": "Senpai wa Otokonoko",
                                "artist": "SubsPlease",
                                "thumbnail_url": "https://i.animepahe.ru/snapshots/299c44601c664ff79eead2e1560afa518a682ef1269560449198b0d8afa1c398.jpg"
                            },
                            {
                                "url": "/anime/?anime_id=4889",
                                "title": "Chiikawa",
                                "artist": "SubsPlease",
                                "thumbnail_url": "https://i.animepahe.ru/snapshots/db3e1fd5d0d7f40a1ccdb04fecd7ace749d064112c7579112f179c635edf7270.jpg"
                            },
                            {
                                "url": "/anime/?anime_id=5602",
                                "title": "Megami no Café Terrace 2nd Season",
                                "artist": "SubsPlease",
                                "thumbnail_url": "https://i.animepahe.ru/snapshots/28940794d9a83be550a651adc1025965e3eb12e48dee7ce24eea57f911398b1f.jpg"
                            },
                            {
                                "url": "/anime/?anime_id=5603",
                                "title": "Giji Harem",
                                "artist": "SubsPlease",
                                "thumbnail_url": "https://i.animepahe.ru/snapshots/c2288f4a74dc41c9f6300a0ef3ee1ef2b94f9f60a44bced63e45af3f573a40f8.jpg"
                            },
                            {
                                "url": "/anime/?anime_id=5598",
                                "title": "Ramen Akaneko",
                                "artist": "SubsPlease",
                                "thumbnail_url": "https://i.animepahe.ru/snapshots/ccb5f296501c824fc6dcfe4a8af70535fcb9eccd2170442d82140a550aa1ebd3.jpg"
                            },
                            {
                                "url": "/anime/?anime_id=5601",
                                "title": "Ore wa Subete wo \"Parry\" suru: Gyaku Kanchigai no Sekai Saikyou wa Boukensha ni Naritai",
                                "artist": "SubsPlease",
                                "thumbnail_url": "https://i.animepahe.ru/snapshots/ff0f56710871ffb353d0605a07755305ce79e3003cc00c0c36fa281ad6ac678f.jpg"
                            },
                            {
                                "url": "/anime/?anime_id=5597",
                                "title": "Tasogare Out Focus",
                                "artist": "SubsPlease",
                                "thumbnail_url": "https://i.animepahe.ru/snapshots/3fdc8ff8e698e0833b153f047b5234c2b5367200b80c06ad5334badb2dfa8417.jpg"
                            },
                            {
                                "url": "/anime/?anime_id=5588",
                                "title": "Isekai Suicide Squad",
                                "artist": "Erai-raws",
                                "thumbnail_url": "https://i.animepahe.ru/snapshots/abec30b4938b0c3c3a7232fcbc62132ab796c49ee11dbd84de422d884fb979d5.jpg"
                            },
                            {
                                "url": "/anime/?anime_id=5599",
                                "title": "Gimai Seikatsu",
                                "artist": "SubsPlease",
                                "thumbnail_url": "https://i.animepahe.ru/snapshots/4d0e7b45bf1176bb556fc4efea3b1150c7502839655833525ce330c21e7f21af.jpg"
                            },
                            {
                                "url": "/anime/?anime_id=5638",
                                "title": "Delico's Nursery",
                                "artist": "SubsPlease",
                                "thumbnail_url": "https://i.animepahe.ru/snapshots/4a44e336a6c1cd478058f5bce110c3f43a24ca35a57b9f38306caf0d6a9ee06c.jpg"
                            }
                        ],
                        "hasNextPage": true
                    }
                ],
                "passed": true
            },
            "latest": {
                "result": [
                    {
                        "animes": [
                            {
                                "url": "/anime/?anime_id=5587",
                                "title": "Code Geass: Dakkan no Rozé",
                                "artist": "Disney_Plus",
                                "thumbnail_url": "https://i.animepahe.ru/snapshots/3c8740c2fa6630e8a96db63d63e7e21a4ec3d8ba3a429df0a393690de6abc82c.jpg"
                            },
                            {
                                "url": "/anime/?anime_id=5584",
                                "title": "Dead Dead Demons Dededede Destruction (ONA)",
                                "artist": "SubsPlease",
                                "thumbnail_url": "https://i.animepahe.ru/snapshots/7ac832382caf39e53677ca8df68a859d49c2ceb616f2ef062314395ecfe7ad3a.jpg"
                            },
                            {
                                "url": "/anime/?anime_id=5606",
                                "title": "Senpai wa Otokonoko",
                                "artist": "SubsPlease",
                                "thumbnail_url": "https://i.animepahe.ru/snapshots/299c44601c664ff79eead2e1560afa518a682ef1269560449198b0d8afa1c398.jpg"
                            },
                            {
                                "url": "/anime/?anime_id=4889",
                                "title": "Chiikawa",
                                "artist": "SubsPlease",
                                "thumbnail_url": "https://i.animepahe.ru/snapshots/db3e1fd5d0d7f40a1ccdb04fecd7ace749d064112c7579112f179c635edf7270.jpg"
                            },
                            {
                                "url": "/anime/?anime_id=5602",
                                "title": "Megami no Café Terrace 2nd Season",
                                "artist": "SubsPlease",
                                "thumbnail_url": "https://i.animepahe.ru/snapshots/28940794d9a83be550a651adc1025965e3eb12e48dee7ce24eea57f911398b1f.jpg"
                            },
                            {
                                "url": "/anime/?anime_id=5603",
                                "title": "Giji Harem",
                                "artist": "SubsPlease",
                                "thumbnail_url": "https://i.animepahe.ru/snapshots/c2288f4a74dc41c9f6300a0ef3ee1ef2b94f9f60a44bced63e45af3f573a40f8.jpg"
                            },
                            {
                                "url": "/anime/?anime_id=5598",
                                "title": "Ramen Akaneko",
                                "artist": "SubsPlease",
                                "thumbnail_url": "https://i.animepahe.ru/snapshots/ccb5f296501c824fc6dcfe4a8af70535fcb9eccd2170442d82140a550aa1ebd3.jpg"
                            },
                            {
                                "url": "/anime/?anime_id=5601",
                                "title": "Ore wa Subete wo \"Parry\" suru: Gyaku Kanchigai no Sekai Saikyou wa Boukensha ni Naritai",
                                "artist": "SubsPlease",
                                "thumbnail_url": "https://i.animepahe.ru/snapshots/ff0f56710871ffb353d0605a07755305ce79e3003cc00c0c36fa281ad6ac678f.jpg"
                            },
                            {
                                "url": "/anime/?anime_id=5597",
                                "title": "Tasogare Out Focus",
                                "artist": "SubsPlease",
                                "thumbnail_url": "https://i.animepahe.ru/snapshots/3fdc8ff8e698e0833b153f047b5234c2b5367200b80c06ad5334badb2dfa8417.jpg"
                            },
                            {
                                "url": "/anime/?anime_id=5588",
                                "title": "Isekai Suicide Squad",
                                "artist": "Erai-raws",
                                "thumbnail_url": "https://i.animepahe.ru/snapshots/abec30b4938b0c3c3a7232fcbc62132ab796c49ee11dbd84de422d884fb979d5.jpg"
                            },
                            {
                                "url": "/anime/?anime_id=5599",
                                "title": "Gimai Seikatsu",
                                "artist": "SubsPlease",
                                "thumbnail_url": "https://i.animepahe.ru/snapshots/4d0e7b45bf1176bb556fc4efea3b1150c7502839655833525ce330c21e7f21af.jpg"
                            },
                            {
                                "url": "/anime/?anime_id=5638",
                                "title": "Delico's Nursery",
                                "artist": "SubsPlease",
                                "thumbnail_url": "https://i.animepahe.ru/snapshots/4a44e336a6c1cd478058f5bce110c3f43a24ca35a57b9f38306caf0d6a9ee06c.jpg"
                            }
                        ],
                        "hasNextPage": true
                    }
                ],
                "passed": true
            },
            "search": {
                "result": [
                    {
                        "animes": [
                            {
                                "url": "/anime/?anime_id=119",
                                "title": "World Trigger",
                                "thumbnail_url": "https://i.animepahe.ru/posters/5a3bd9bf6b59f52791ed7b7c05a300a1b9e9007a625d85124ccd7b2284cba8a0.jpg"
                            },
                            {
                                "url": "/anime/?anime_id=2064",
                                "title": "World Fool News (TV)",
                                "thumbnail_url": "https://i.animepahe.ru/posters/fa9d124c722e9299a10cb95a7f21a020c743aee11fffdfc70e359174a6e21fc9.jpg"
                            },
                            {
                                "url": "/anime/?anime_id=1473",
                                "title": "Seiken Tsukai no World Break",
                                "thumbnail_url": "https://i.animepahe.ru/posters/bba0a45b28c71d6d667373e8252fc7c7e081f0161a1d5de92c99f242528a1325.jpg"
                            },
                            {
                                "url": "/anime/?anime_id=2043",
                                "title": "World Fool News (TV) Part II",
                                "thumbnail_url": "https://i.animepahe.ru/posters/0073b9c98ead3b7f10842dbec19670b5f21fddbc63404466bae6b833c2328195.jpg"
                            },
                            {
                                "url": "/anime/?anime_id=4175",
                                "title": "World Trigger 2nd Season",
                                "thumbnail_url": "https://i.animepahe.ru/posters/50d7865d198d0a2d7faee377b50698e3a16934f63c345dad425975146ac03778.jpg"
                            },
                            {
                                "url": "/anime/?anime_id=4200",
                                "title": "World Witches Hasshin Shimasu!",
                                "thumbnail_url": "https://i.animepahe.ru/posters/043989368c94192bfdb1843bbf32ce2a798c3acc82b1deea803fd02e3bd67b07.jpg"
                            },
                            {
                                "url": "/anime/?anime_id=4524",
                                "title": "World Trigger 3rd Season",
                                "thumbnail_url": "https://i.animepahe.ru/posters/342aeeeafea0be4d7b0d073ea0911ad86bea88261c782ea64211c470073eab08.jpg"
                            },
                            {
                                "url": "/anime/?anime_id=5229",
                                "title": "World Dai Star",
                                "thumbnail_url": "https://i.animepahe.ru/posters/e9a0985f593a33302d983d125b3fd44d1124c540176fcfad6296a0b819709319.jpg"
                            }
                        ],
                        "hasNextPage": false
                    }
                ],
                "passed": true
            },
            "details": {
                "result": {
                    "url": "/anime/?anime_id=5587",
                    "title": "Code Geass: Dakkan no Rozé",
                    "author": "Sunrise",
                    "description": "After the supposed death of its 99th emperor, the Holy Britannian Empire broke up, and the areas it controlled finally regained their independence. While most joined the United Federation of Nations, a group aiming to create everlasting peace, remnants of the oppressive empire continue to exist. One such faction, Neo-Britannia, has taken over Japan's Hokkaido island after killing its governor, Juugo Sumeragi. The Seven Shining Stars, a resistance group in Hokkaido, finds itself at an impasse as it struggles to find a way to defeat the Neo-Britannian Empire. As a last resort, it enlists the aid of the Nameless Mercenaries: brothers Rozé, a genius strategist; and Ash, an exceptional Knightmare pilot. Though Rozé and Ash are Britannian, they have made a name for themselves by protecting the Japanese and killing the empire's officials. With their help, the resistance may finally be able to recapture its territory and prevent another reign of terror.",
                    "genre": "Action, Drama, Sci-Fi",
                    "status": 1,
                    "status_name": "ONGOING",
                    "thumbnail_url": "https://i.animepahe.ru/posters/d6e151ff862b16b60e8afc23cfd316cbfd3fa410e30bb2e6ff6143a4a25d84ed.jpg",
                    "initialized": true
                },
                "passed": true
            },
            "episodes": {
                "result": [
                    {
                        "url": "/play/0b1fae00-ba96-24b3-224d-8d0de7ea1429/fbb54b035307cf1cf7d116216260733e21b6bff648804aa3a5465775c69c7545",
                        "name": "Episode 9",
                        "date_upload": 1723794111000,
                        "episode_number": 9.0
                    },
                    {
                        "url": "/play/0b1fae00-ba96-24b3-224d-8d0de7ea1429/c3dde1b7931c7a68ac0f09a81c5c179da69aad258e2eb9605f980c398cb95857",
                        "name": "Episode 8",
                        "date_upload": 1723187630000,
                        "episode_number": 8.0
                    }
                ],
                "passed": true
            },
            "videos": {
                "result": [
                    {
                        "url": "https://na-99.files.nextcdn.org/get/99/01/5585d32072962e340e59f03edaf44773683dbc8342c6f2c37bcd519bbb4323dc?file=AnimePahe_Code_Geass_-_Dakkan_no_Roze_-_09_1080p_Disney_Plus.mp4&token=r6HwzeoYm_sSY5stLPUPpA&expires=1723826388",
                        "quality": "Disney_Plus · 1080p",
                        "videoUrl": "https://na-99.files.nextcdn.org/get/99/01/5585d32072962e340e59f03edaf44773683dbc8342c6f2c37bcd519bbb4323dc?file=AnimePahe_Code_Geass_-_Dakkan_no_Roze_-_09_1080p_Disney_Plus.mp4&token=r6HwzeoYm_sSY5stLPUPpA&expires=1723826388"
                    },
                    {
                        "url": "https://na-99.files.nextcdn.org/get/99/01/56a1ccdc0b3d0049b9b4c9564fc4ef4cd10ddc84e44ef2636b6d529027f17c85?file=AnimePahe_Code_Geass_-_Dakkan_no_Roze_Eng_Dub_-_09_1080p_Disney_Plus.mp4&token=sHtRNN-zeoEMW6TCbvkefA&expires=1723826393",
                        "quality": "Disney_Plus · 1080p eng",
                        "videoUrl": "https://na-99.files.nextcdn.org/get/99/01/56a1ccdc0b3d0049b9b4c9564fc4ef4cd10ddc84e44ef2636b6d529027f17c85?file=AnimePahe_Code_Geass_-_Dakkan_no_Roze_Eng_Dub_-_09_1080p_Disney_Plus.mp4&token=sHtRNN-zeoEMW6TCbvkefA&expires=1723826393"
                    },
                    {
                        "url": "https://na-99.files.nextcdn.org/get/99/01/45a1b40c1f3a34caaaf13b62a71d7747f0e67e495b989a087a29dc2a13ec3f8e?file=AnimePahe_Code_Geass_-_Dakkan_no_Roze_-_09_720p_Disney_Plus.mp4&token=BcR1DwzUSI5VxtwOSyvJ6A&expires=1723826387",
                        "quality": "Disney_Plus · 720p",
                        "videoUrl": "https://na-99.files.nextcdn.org/get/99/01/45a1b40c1f3a34caaaf13b62a71d7747f0e67e495b989a087a29dc2a13ec3f8e?file=AnimePahe_Code_Geass_-_Dakkan_no_Roze_-_09_720p_Disney_Plus.mp4&token=BcR1DwzUSI5VxtwOSyvJ6A&expires=1723826387"
                    },
                    {
                        "url": "https://na-99.files.nextcdn.org/get/99/01/47f501cd10d25676f2f868d3b826a842a3d41dec2b0ac3a4f2ef3f100493b694?file=AnimePahe_Code_Geass_-_Dakkan_no_Roze_-_09_360p_Disney_Plus.mp4&token=3YpNiD0yhuAuRyoZIgHmSQ&expires=1723826385",
                        "quality": "Disney_Plus · 360p",
                        "videoUrl": "https://na-99.files.nextcdn.org/get/99/01/47f501cd10d25676f2f868d3b826a842a3d41dec2b0ac3a4f2ef3f100493b694?file=AnimePahe_Code_Geass_-_Dakkan_no_Roze_-_09_360p_Disney_Plus.mp4&token=3YpNiD0yhuAuRyoZIgHmSQ&expires=1723826385"
                    },
                    {
                        "url": "https://na-99.files.nextcdn.org/get/99/01/b62a08dba11a833ef7ce08177703c71899edd86d27373617631a729e876cd0ba?file=AnimePahe_Code_Geass_-_Dakkan_no_Roze_Eng_Dub_-_09_720p_Disney_Plus.mp4&token=z00wa9XLnDnMcctMV-Wu1g&expires=1723826391",
                        "quality": "Disney_Plus · 720p eng",
                        "videoUrl": "https://na-99.files.nextcdn.org/get/99/01/b62a08dba11a833ef7ce08177703c71899edd86d27373617631a729e876cd0ba?file=AnimePahe_Code_Geass_-_Dakkan_no_Roze_Eng_Dub_-_09_720p_Disney_Plus.mp4&token=z00wa9XLnDnMcctMV-Wu1g&expires=1723826391"
                    },
                    {
                        "url": "https://na-99.files.nextcdn.org/get/99/01/48ef77cac3f3024dd3c0dddbdb5ea787e012fd3ad477f910d4a009e69788b445?file=AnimePahe_Code_Geass_-_Dakkan_no_Roze_Eng_Dub_-_09_360p_Disney_Plus.mp4&token=InKCpOjL_0TiNjyfJyp8Yg&expires=1723826390",
                        "quality": "Disney_Plus · 360p eng",
                        "videoUrl": "https://na-99.files.nextcdn.org/get/99/01/48ef77cac3f3024dd3c0dddbdb5ea787e012fd3ad477f910d4a009e69788b445?file=AnimePahe_Code_Geass_-_Dakkan_no_Roze_Eng_Dub_-_09_360p_Disney_Plus.mp4&token=InKCpOjL_0TiNjyfJyp8Yg&expires=1723826390"
                    }
                ],
                "passed": true
            }
        }
    }
]